Workbook

Sheet How to review
A1: Clinical review — Critical Care Physiology
A3: What this is | B3: Every teaching claim in the app, one row each: reference values, all lesson narration, challenge questions with their answers and explanations, real clinical media captions and overlays, and the descriptions shown when a 3D label is tapped.
A4: What to fill in | B4: Only the two yellow columns on the Review sheet: Verdict (pick OK, Change or Remove from the list) and Reviewer comment (what is wrong and what it should say).
A5: Where to look | B5: "Where in the app" names the module and screen. Overlay rows ask you to check placement on the image in the app itself.
A6: Progress | B6: The Summary sheet counts verdicts per section as you go.
A7: Source | B7: Generated from the app source by app/scripts/review-packet.ts (751 rows). Regenerated on every site build; the IDs stay stable so comments can be matched back.
A9: Example row (not part of the review)
A10: Section | B10: ID | C10: Where in the app | D10: Item | E10: Content to review | F10: Verdict | G10: Reviewer comment
A11: 1 Reference values | B11: vent:PEEP | C11: Ventilator › Normal values › Settings | D11: PEEP | E11: 5 cmH₂O — Physiological minimum… | F11: Change | G11: Say "typical starting PEEP" rather than "physiological minimum".

Sheet Summary
A1: Section | B1: Items | C1: OK | D1: Change | E1: Remove | F1: Not yet reviewed | G1: % reviewed
A2: 1 Reference values | B2: =COUNTIF(Review!$A$2:$A$752,$A2) -> 76 | C2: =COUNTIFS(Review!$A$2:$A$752,$A2,Review!$G$2:$G$752,"OK") -> 0 | D2: =COUNTIFS(Review!$A$2:$A$752,$A2,Review!$G$2:$G$752,"Change") -> 0 | E2: =COUNTIFS(Review!$A$2:$A$752,$A2,Review!$G$2:$G$752,"Remove") -> 0 | F2: =B2-C2-D2-E2 -> 76 | G2: =IF(B2=0,0,(C2+D2+E2)/B2) -> 0
A3: 2 Lesson narration | B3: =COUNTIF(Review!$A$2:$A$752,$A3) -> 342 | C3: =COUNTIFS(Review!$A$2:$A$752,$A3,Review!$G$2:$G$752,"OK") -> 0 | D3: =COUNTIFS(Review!$A$2:$A$752,$A3,Review!$G$2:$G$752,"Change") -> 0 | E3: =COUNTIFS(Review!$A$2:$A$752,$A3,Review!$G$2:$G$752,"Remove") -> 0 | F3: =B3-C3-D3-E3 -> 342 | G3: =IF(B3=0,0,(C3+D3+E3)/B3) -> 0
A4: 3 Challenge cases | B4: =COUNTIF(Review!$A$2:$A$752,$A4) -> 80 | C4: =COUNTIFS(Review!$A$2:$A$752,$A4,Review!$G$2:$G$752,"OK") -> 0 | D4: =COUNTIFS(Review!$A$2:$A$752,$A4,Review!$G$2:$G$752,"Change") -> 0 | E4: =COUNTIFS(Review!$A$2:$A$752,$A4,Review!$G$2:$G$752,"Remove") -> 0 | F4: =B4-C4-D4-E4 -> 80 | G4: =IF(B4=0,0,(C4+D4+E4)/B4) -> 0
A5: 4 Real clinical media | B5: =COUNTIF(Review!$A$2:$A$752,$A5) -> 64 | C5: =COUNTIFS(Review!$A$2:$A$752,$A5,Review!$G$2:$G$752,"OK") -> 0 | D5: =COUNTIFS(Review!$A$2:$A$752,$A5,Review!$G$2:$G$752,"Change") -> 0 | E5: =COUNTIFS(Review!$A$2:$A$752,$A5,Review!$G$2:$G$752,"Remove") -> 0 | F5: =B5-C5-D5-E5 -> 64 | G5: =IF(B5=0,0,(C5+D5+E5)/B5) -> 0
A6: 5 Label descriptions | B6: =COUNTIF(Review!$A$2:$A$752,$A6) -> 189 | C6: =COUNTIFS(Review!$A$2:$A$752,$A6,Review!$G$2:$G$752,"OK") -> 0 | D6: =COUNTIFS(Review!$A$2:$A$752,$A6,Review!$G$2:$G$752,"Change") -> 0 | E6: =COUNTIFS(Review!$A$2:$A$752,$A6,Review!$G$2:$G$752,"Remove") -> 0 | F6: =B6-C6-D6-E6 -> 189 | G6: =IF(B6=0,0,(C6+D6+E6)/B6) -> 0
A7: Total | B7: =SUM(B2:B6) -> 751 | C7: =SUM(C2:C6) -> 0 | D7: =SUM(D2:D6) -> 0 | E7: =SUM(E2:E6) -> 0 | F7: =SUM(F2:F6) -> 751 | G7: =IF(B7=0,0,(C7+D7+E7)/B7) -> 0

Sheet Review
A1: Section | B1: ID | C1: Where in the app | D1: Item | E1: Content to review | F1: Source / credit | G1: Verdict | H1: Reviewer comment
A2: 1 Reference values | B2: vent:Tidal volume | C2: Ventilator › Normal values › Settings — adult, lung-protective starting point | D2: Tidal volume | E2: 6–8 mL/kg PBW — ARDS 4–6 (start at 6). Always per predicted body weight, never actual weight.
A3: 1 Reference values | B3: vent:Predicted body weight | C3: Ventilator › Normal values › Settings — adult, lung-protective starting point | D3: Predicted body weight | E3: from height kg — Men 50 + 0.91 × (height cm − 152.4); women 45.5 + 0.91 × (height cm − 152.4). Height, not weight, sets lung size.
A4: 1 Reference values | B4: vent:Respiratory rate | C4: Ventilator › Normal values › Settings — adult, lung-protective starting point | D4: Respiratory rate | E4: 12–20 /min — ARDS up to 35 to hold pH; obstructive disease lower (8–12) to allow exhalation.
A5: 1 Reference values | B5: vent:Minute ventilation | C5: Ventilator › Normal values › Settings — adult, lung-protective starting point | D5: Minute ventilation | E5: 5–8 L/min — ≈ 100 mL/kg PBW/min. Higher needs (sepsis, acidosis) push it up.
A6: 1 Reference values | B6: vent:PEEP | C6: Ventilator › Normal values › Settings — adult, lung-protective starting point | D6: PEEP | E6: 5 cmH₂O — Physiological minimum. ARDS: higher per the PEEP/FiO₂ table (often 8–18).
A7: 1 Reference values | B7: vent:FiO₂ | C7: Ventilator › Normal values › Settings — adult, lung-protective starting point | D7: FiO₂ | E7: 0.21–1.0 — Start 1.0 after intubation, then the lowest FiO₂ that meets the SpO₂ target; aim < 0.6.
A8: 1 Reference values | B8: vent:I:E ratio | C8: Ventilator › Normal values › Settings — adult, lung-protective starting point | D8: I:E ratio | E8: 1:2 — Obstructive disease 1:3 to 1:5 to give time to exhale.
A9: 1 Reference values | B9: vent:Inspiratory time | C9: Ventilator › Normal values › Settings — adult, lung-protective starting point | D9: Inspiratory time | E9: 0.8–1.2 s
A10: 1 Reference values | B10: vent:Peak inspiratory flow (VC) | C10: Ventilator › Normal values › Settings — adult, lung-protective starting point | D10: Peak inspiratory flow (VC) | E10: 40–60 L/min — Higher (60–80+) in obstruction to shorten inspiration.
A11: 1 Reference values | B11: vent:Plateau pressure | C11: Ventilator › Normal values › Measured mechanics | D11: Plateau pressure | E11: ≤ 30 (ideally < 28) cmH₂O — Alveolar pressure at end-inspiration — needs an inspiratory hold to measure.
A12: 1 Reference values | B12: vent:Driving pressure (Pplat − PEEP) | C12: Ventilator › Normal values › Measured mechanics | D12: Driving pressure (Pplat − PEEP) | E12: ≤ 15 cmH₂O — The strongest single predictor of ventilator-induced lung injury.
A13: 1 Reference values | B13: vent:Peak inspiratory pressure | C13: Ventilator › Normal values › Measured mechanics | D13: Peak inspiratory pressure | E13: < 35 cmH₂O — PIP − Pplat ≤ 5 is normal; > 10 = high airway resistance (kinked tube, secretions, bronchospasm).
... A499: 3 Challenge cases | B499: lines-case:c-goal-sepsis | C499: Lines › Challenge › Warm, vasodilated and hypotensive | D499: What does the waveform suggest is the main problem? | E499: Septic shock after 2 L of fluid. MAP in the high 50s, low diastolic, low dicrotic notch. Answer: Low vascular tone — a vasopressor is needed. Other options: Pump failure — start an inotrope | Severe hypovolaemia only | Tamponade. Explanation: Low diastolic pressure with a notch near the diastolic level and a high heart rate: vasoplegia. Norepinephrine restores tone. PPV is still just above 13 %, so some fluid may help alongside it.
A500: 4 Real clinical media | B500: 3fd337c1:caption | C500: Real media › xray | D500: Portable AP film, ventilated patient — caption | E500: Endotracheal tube in the trachea, ECG leads and lines; patchy airspace opacities in both lungs (COVID-19 pneumonia) — the pattern the ARDS lesson draws. | F500: Institute for Diagnostic and Interventional Radiology, Hannover Medical School (MHH), Germany. COVID-19 Image Repository — https://github.com/ml-workgroup/covid-19-image-repository (copy retrieved from https://github.com/ieee8023/covid-chestxray-dataset, images/<id>.jpg). CC BY 3.0
A501: 4 Real clinical media | B501: 3fd337c1:look | C501: Real media › xray | D501: Portable AP film, ventilated patient — look for | E501: Tube tip above the carina · Bilateral patchy opacities · Heart size not enlarged · Lines and leads crossing the film | F501: Institute for Diagnostic and Interventional Radiology, Hannover Medical School (MHH), Germany. COVID-19 Image Repository — https://github.com/ml-workgroup/covid-19-image-repository (copy retrieved from https://github.com/ieee8023/covid-chestxray-dataset, images/<id>.jpg). CC BY 3.0
A502: 4 Real clinical media | B502: 98c24e39:caption | C502: Real media › xray | D502: Portable AP film, severe bilateral disease — caption | E502: Dense opacities in both lungs with many tubes, lines and leads over the chest — typical of a sick ICU patient; the lines are not lung disease. | F502: Institute for Diagnostic and Interventional Radiology, Hannover Medical School (MHH), Germany. COVID-19 Image Repository — https://github.com/ml-workgroup/covid-19-image-repository (copy retrieved from https://github.com/ieee8023/covid-chestxray-dataset, images/<id>.jpg). CC BY 3.0
A503: 4 Real clinical media | B503: 98c24e39:look | C503: Real media › xray | D503: Portable AP film, severe bilateral disease — look for | E503: Opacities in both lungs · Many external lines — follow each one · Borders of heart and diaphragm blurred | F503: Institute for Diagnostic and Interventional Radiology, Hannover Medical School (MHH), Germany. COVID-19 Image Repository — https://github.com/ml-workgroup/covid-19-image-repository (copy retrieved from https://github.com/ieee8023/covid-chestxray-dataset, images/<id>.jpg). CC BY 3.0
A504: 4 Real clinical media | B504: bfefde5d:caption | C504: Real media › xray | D504: Bedside film, lungs largely clear — caption | E504: A bedside ("Bettaufnahme") film with largely clear lungs and an implanted port in the left upper chest — a baseline to compare against. | F504: Institute for Diagnostic and Interventional Radiology, Hannover Medical School (MHH), Germany. COVID-19 Image Repository — https://github.com/ml-workgroup/covid-19-image-repository (copy retrieved from https://github.com/ieee8023/covid-chestxray-dataset, images/<id>.jpg). CC BY 3.0
A505: 4 Real clinical media | B505: bfefde5d:look | C505: Real media › xray | D505: Bedside film, lungs largely clear — look for | E505: Lung markings reach the periphery · Sharp heart and diaphragm borders · Port catheter from the left chest wall | F505: Institute for Diagnostic and Interventional Radiology, Hannover Medical School (MHH), Germany. COVID-19 Image Repository — https://github.com/ml-workgroup/covid-19-image-repository (copy retrieved from https://github.com/ieee8023/covid-chestxray-dataset, images/<id>.jpg). CC BY 3.0
A506: 4 Real clinical media | B506: alines:caption | C506: Real media › lus | D506: A-lines: aerated lung — caption | E506: Longitudinal anterior chest scan in aerated lung: horizontal repeats of the pleural line (A-lines). Faint in this clip. | F506: Ana Luisa Silveira Vieira, José Muniz Pazeli Júnior, Marcus Gomes Bastos. “Role of point-of-care ultrasound during the COVID-19 pandemic: our recommendations in the management of dialytic patients”, The Ultrasound Journal 12:30 (2020), https://doi.org/10.1186/s13089-020-00177-4 (clip via https://github.com/jannisborn/covid19_ultrasound). CC BY 4.0
A507: 4 Real clinical media | B507: alines:look | C507: Real media › lus | D507: A-lines: aerated lung — look for | E507: Bright pleural line · Horizontal repeats at equal spacing · No vertical B-lines | F507: Ana Luisa Silveira Vieira, José Muniz Pazeli Júnior, Marcus Gomes Bastos. “Role of point-of-care ultrasound during the COVID-19 pandemic: our recommendations in the management of dialytic patients”, The Ultrasound Journal 12:30 (2020), https://doi.org/10.1186/s13089-020-00177-4 (clip via https://github.com/jannisborn/covid19_ultrasound). CC BY 4.0
A508: 4 Real clinical media | B508: blines:caption | C508: Real media › lus | D508: B-lines — caption | E508: Right lateral chest in COVID-19 pneumonia: vertical bright B-lines from the pleural line to the bottom of the screen, alternating with A-lines, and a thickened pleura. | F508: Giovanni Volpicelli, Luna Gargani. “Sonographic signs and patterns of COVID-19 pneumonia”, The Ultrasound Journal 12:22 (2020), https://doi.org/10.1186/s13089-020-00171-w (clip via https://github.com/jannisborn/covid19_ultrasound). CC BY 4.0
A509: 4 Real clinical media | B509: blines:look | C509: Real media › lus | D509: B-lines — look for | E509: Vertical lines from the pleura · They reach the bottom of the screen · They move with lung sliding | F509: Giovanni Volpicelli, Luna Gargani. “Sonographic signs and patterns of COVID-19 pneumonia”, The Ultrasound Journal 12:22 (2020), https://doi.org/10.1186/s13089-020-00171-w (clip via https://github.com/jannisborn/covid19_ultrasound). CC BY 4.0
A510: 4 Real clinical media | B510: whitelung:caption | C510: Real media › lus | D510: White lung: confluent B-lines — caption | E510: H1N1 pneumonia, lateral mid-chest: confluent B-lines ("white lung") with superficial consolidation and a thickened pleural line. | F510: Americo Testa, Gino Soldati, Roberto Copetti, Rosangela Giannuzzi, Grazia Portale, Nicolò Gentiloni-Silveri. “Early recognition of the 2009 pandemic influenza A (H1N1) pneumonia by chest ultrasound”, Critical Care 16:R30 (2012), https://doi.org/10.1186/cc11201 (clip via https://github.com/jannisborn/covid19_ultrasound). CC BY 2.0
A511: 4 Real clinical media | B511: whitelung:look | C511: Real media › lus | D511: White lung: confluent B-lines — look for | E511: No black gaps between B-lines · Irregular pleural line · Small subpleural consolidations | F511: Americo Testa, Gino Soldati, Roberto Copetti, Rosangela Giannuzzi, Grazia Portale, Nicolò Gentiloni-Silveri. “Early recognition of the 2009 pandemic influenza A (H1N1) pneumonia by chest ultrasound”, Critical Care 16:R30 (2012), https://doi.org/10.1186/cc11201 (clip via https://github.com/jannisborn/covid19_ultrasound). CC BY 2.0
... A563: 4 Real clinical media | B563: lus-sliding-gillman2012:marks | C563: Real media › ptxlus | D563: Normal lung sliding — overlay labels (check placement in the app) | E563: landmark: Chest wall · landmark: Pleural line — watch it shimmer | F563: Gillman L, Kirkpatrick A. “Portable bedside ultrasound: the visual stethoscope of the 21st century”, Scandinavian Journal of Trauma, Resuscitation and Emergency Medicine 20:18 (2012), https://doi.org/10.1186/1757-7241-20-18 — supplementary video S1 (“Normal Lung Sliding”), via Wikimedia Commons https://commons.wikimedia.org/wiki/File:Portable-bedside-ultrasound-the-visual-stethoscope-of-the-21st-century-1757-7241-20-18-S1.ogv. CC BY 2.0
A564: 5 Label descriptions | B564: label:AAA — abdominal aortic aneurysm | C564: 3D labels › abdomen | D564: AAA — abdominal aortic aneurysm | E564: Abdominal aortic aneurysm — the aorta wider than 3 cm. Rupture risk rises sharply with size.
A565: 5 Label descriptions | B565: label:ACoA | C565: 3D labels › neuro | D565: ACoA | E565: Anterior communicating artery — joins the two anterior cerebral arteries; the commonest site of berry aneurysms.
A566: 5 Label descriptions | B566: label:Aerated alveolus | C566: 3D labels › vent | D566: Aerated alveolus | E566: An open, ventilated air sac taking part in gas exchange.
A567: 5 Label descriptions | B567: label:Afferent arteriole (blood in) | C567: 3D labels › labs | D567: Afferent arteriole (blood in) | E567: Brings blood into the glomerulus; it constricts or dilates to hold filtration steady.
A568: 5 Label descriptions | B568: label:Alveolar duct | C568: 3D labels › vent, abg | D568: Alveolar duct | E568: Small airway leading into a cluster of alveoli.
A569: 5 Label descriptions | B569: label:Alveolar gas | C569: 3D labels › vent | D569: Alveolar gas | E569: The gas in the air sacs, where oxygen and carbon dioxide exchange with capillary blood.
A570: 5 Label descriptions | B570: label:Anterior tibial → dorsalis pedis | C570: 3D labels › lines | D570: Anterior tibial → dorsalis pedis | E570: Runs down the front of the leg to the top of the foot, where the dorsalis pedis pulse is felt.
A571: 5 Label descriptions | B571: label:Aorta | C571: 3D labels › lines, heart, abdomen | D571: Aorta | E571: The main artery leaving the left ventricle. Arterial lines and blood pressure measure the pressure in its branches.
A572: 5 Label descriptions | B572: label:Aquaporin | C572: 3D labels › labs | D572: Aquaporin | E572: Aquaporin-4 water channel. Lets water cross in seconds. Water always moves toward the side with more dissolved particles.
A573: 5 Label descriptions | B573: label:Arterial cannula | C573: 3D labels › lines | D573: Arterial cannula | E573: A 20-gauge cannula in the radial artery. Its trace is only as good as its patency, flush and zeroing.
A574: 5 Label descriptions | B574: label:Arterial end | C574: 3D labels › labs | D574: Arterial end | E574: Blood enters the capillary oxygen-rich at arterial pressure.
A575: 5 Label descriptions | B575: label:Arteriole — an ABG samples this blood | C575: 3D labels › abg | D575: Arteriole — an ABG samples this blood | E575: Arterial blood: an arterial blood gas measures the oxygen, CO₂ and acid–base status delivered to the tissues.
... A752: 5 Label descriptions | B752: label:VSD — ventricular septal defect | C752: 3D labels › heart | D752: VSD — ventricular septal defect | E752: Ventricular septal defect — a hole in the septum between the ventricles. Flow normally runs left to right; it reverses if right-sided pressures exceed left.
